{
  "posts": [
    {
      "id": 1,
      "title": "json-server",
      "author": "typicode"
    },
    {
      "id": 2,
      "title": "json-server2",
      "author": "typicode"
    },
    {
      "id": 3,
      "title": "json-server2",
      "author": "typicode"
    },
    {
      "title": "xxx",
      "author": "yyyy",
      "id": 4
    },
    {
      "title": "xxx",
      "author": "yyyy",
      "id": 5
    },
    {
      "title": "xxx",
      "author": "yyyy",
      "id": 6
    },
    {
      "title": "xxx",
      "author": "yyyy",
      "id": 7
    },
    {
      "title": "xxx",
      "author": "yyyy",
      "id": 8
    },
    {
      "title": "xxx",
      "author": "yyyy",
      "id": 9
    },
    {
      "title": "xxx",
      "author": "yyyy",
      "id": 10
    }
  ],
  "comments": [
    {
      "body": "abcdefg",
      "postId": 2,
      "id": 3
    },
    {
      "id": 4
    },
    {
      "body": "aaaa",
      "postId": 2,
      "id": 5
    },
    {
      "body": "aaaa",
      "postId": 2,
      "id": 6
    }
  ],
  "profile": {
    "name": "typicode"
  }
}